fastapi_db_mixins/__init__.py
fastapi_db_mixins/main.py
fastapi_db_mixins-1.1.4.dist-info/LICENSE
fastapi_db_mixins-1.1.4.dist-info/METADATA
fastapi_db_mixins-1.1.4.dist-info/WHEEL
fastapi_db_mixins-1.1.4.dist-info/top_level.txt
fastapi_db_mixins-1.1.4.dist-info/RECORD
