Metadata-Version: 2.2
Name: fastapi-db-mixins
Version: 1.1.4
Summary: FastAPI database mixins
License-File: LICENSE
Requires-Dist: sqlalchemy
Dynamic: requires-dist
Dynamic: summary
